nvtk_ssm/__init__.py
nvtk_ssm/doubleA5.py
nvtk_ssm/ssm.py
nvtk_ssm/svglue.py
nvtk_sitesheets-0.1.0.dist-info/entry_points.txt
nvtk_sitesheets-0.1.0.dist-info/WHEEL
nvtk_sitesheets-0.1.0.dist-info/METADATA
nvtk_sitesheets-0.1.0.dist-info/RECORD
